channel_app/__init__.py
channel_app/app/__init__.py
channel_app/app/order/__init__.py
channel_app/app/order/service.py
channel_app/app/product/__init__.py
channel_app/app/product/service.py
channel_app/app/product_image/__init__.py
channel_app/app/product_image/service.py
channel_app/app/product_price/__init__.py
channel_app/app/product_price/service.py
channel_app/app/product_stock/__init__.py
channel_app/app/product_stock/service.py
channel_app/app/setup/__init__.py
channel_app/app/setup/service.py
channel_app/channel/__init__.py
channel_app/channel/integration.py
channel_app/channel/commands/__init__.py
channel_app/channel/commands/product_categories.py
channel_app/channel/commands/product_images.py
channel_app/channel/commands/product_prices.py
channel_app/channel/commands/product_stocks.py
channel_app/channel/commands/products.py
channel_app/channel/commands/setup.py
channel_app/channel/commands/orders/__init__.py
channel_app/channel/commands/orders/orders.py
channel_app/core/__init__.py
channel_app/core/clients.py
channel_app/core/commands.py
channel_app/core/data.py
channel_app/core/integration.py
channel_app/core/products.py
channel_app/core/settings.py
channel_app/core/tests.py
channel_app/core/utilities.py
channel_app/omnitron/__init__.py
channel_app/omnitron/batch_request.py
channel_app/omnitron/constants.py
channel_app/omnitron/exceptions.py
channel_app/omnitron/integration.py
channel_app/omnitron/commands/__init__.py
channel_app/omnitron/commands/batch_requests.py
channel_app/omnitron/commands/error_reports.py
channel_app/omnitron/commands/integration_actions.py
channel_app/omnitron/commands/product_categories.py
channel_app/omnitron/commands/product_images.py
channel_app/omnitron/commands/product_prices.py
channel_app/omnitron/commands/product_stocks.py
channel_app/omnitron/commands/products.py
channel_app/omnitron/commands/setup.py
channel_app/omnitron/commands/orders/__init__.py
channel_app/omnitron/commands/orders/addresses.py
channel_app-0.0.156.dist-info/METADATA
channel_app-0.0.156.dist-info/WHEEL
channel_app-0.0.156.dist-info/top_level.txt
channel_app-0.0.156.dist-info/RECORD
