Metadata-Version: 2.1
Name: channel-app
Version: 0.0.156
Summary: Channel app for Sales Channels
Home-page: https://github.com/akinon/channel_app
Author: akinonteam
Classifier: Development Status :: 5 - Production/Stable
Requires-Python: >=3.5
Requires-Dist: requests
